multi_stock_api/__init__.py
multi_stock_api/app.py
multi_stock_api/configurations.py
multi_stock_api/external_api_access.py
multi_stock_api/helpers.py
multi_stock_api/mappers.py
multi_stock_api/models.py
multi_stock_api-0.1.3.dist-info/LICENSE
multi_stock_api-0.1.3.dist-info/METADATA
multi_stock_api-0.1.3.dist-info/WHEEL
multi_stock_api-0.1.3.dist-info/top_level.txt
multi_stock_api-0.1.3.dist-info/RECORD
